ai_slop_detector-2.6.3.dist-info/licenses/LICENSE
slop_detector/__init__.py
slop_detector/ci_gate.py
slop_detector/cli.py
slop_detector/config.py
slop_detector/core.py
slop_detector/decorators.py
slop_detector/git_integration.py
slop_detector/history.py
slop_detector/models.py
slop_detector/question_generator.py
slop_detector/api/__init__.py
slop_detector/api/models.py
slop_detector/api/server.py
slop_detector/auth/__init__.py
slop_detector/auth/audit.py
slop_detector/auth/rbac.py
slop_detector/auth/session.py
slop_detector/auth/sso.py
slop_detector/languages/__init__.py
slop_detector/languages/base.py
slop_detector/languages/python_analyzer.py
slop_detector/metrics/__init__.py
slop_detector/metrics/context_jargon.py
slop_detector/metrics/ddc.py
slop_detector/metrics/docstring_inflation.py
slop_detector/metrics/hallucination_deps.py
slop_detector/metrics/inflation.py
slop_detector/metrics/ldr.py
slop_detector/ml/__init__.py
slop_detector/ml/classifier.py
slop_detector/ml/data_collector.py
slop_detector/ml/synthetic_generator.py
slop_detector/ml/training_data.py
slop_detector/patterns/__init__.py
slop_detector/patterns/base.py
slop_detector/patterns/cross_language.py
slop_detector/patterns/placeholder.py
slop_detector/patterns/registry.py
slop_detector/patterns/structural.py
ai_slop_detector-2.6.3.dist-info/METADATA
ai_slop_detector-2.6.3.dist-info/WHEEL
ai_slop_detector-2.6.3.dist-info/entry_points.txt
ai_slop_detector-2.6.3.dist-info/top_level.txt
ai_slop_detector-2.6.3.dist-info/RECORD
