Metadata-Version: 2.4
Name: ai-slop-detector
Version: 2.6.3
Summary: Evidence-based static analyzer for detecting AI-generated code quality issues with context-aware validation
Author-email: Flamehaven Labs <info@flamehaven.space>
License: MIT
Project-URL: Homepage, https://github.com/flamehaven/ai-slop-detector
Project-URL: Documentation, https://ai-slop-detector.readthedocs.io
Project-URL: Repository, https://github.com/flamehaven/ai-slop-detector
Project-URL: Bug Tracker, https://github.com/flamehaven/ai-slop-detector/issues
Keywords: ai,code-quality,static-analysis,slop-detection,code-review
Classifier: Development Status :: 4 - Beta
Classifier: Intended Audience :: Developers
Classifier: License :: OSI Approved :: MIT License
Classifier: Programming Language :: Python :: 3
Classifier: Programming Language :: Python :: 3.8
Classifier: Programming Language :: Python :: 3.9
Classifier: Programming Language :: Python :: 3.10
Classifier: Programming Language :: Python :: 3.11
Classifier: Programming Language :: Python :: 3.12
Classifier: Topic :: Software Development :: Quality Assurance
Requires-Python: >=3.8
License-File: LICENSE
Requires-Dist: pyyaml>=6.0
Requires-Dist: radon>=6.0.1
Requires-Dist: jinja2>=3.1.0
Requires-Dist: fastapi>=0.109.0
Requires-Dist: uvicorn[standard]>=0.27.0
Requires-Dist: pydantic>=2.5.0
Requires-Dist: rich>=13.0
Provides-Extra: ml
Requires-Dist: scikit-learn>=1.3.0; extra == "ml"
Requires-Dist: xgboost>=2.0.0; extra == "ml"
Requires-Dist: numpy>=1.24.0; extra == "ml"
Provides-Extra: dev
Requires-Dist: pytest>=7.0.0; extra == "dev"
Requires-Dist: pytest-cov>=4.0.0; extra == "dev"
Requires-Dist: black>=23.0.0; extra == "dev"
Requires-Dist: ruff>=0.1.0; extra == "dev"
Requires-Dist: mypy>=1.0.0; extra == "dev"
Dynamic: license-file
